libpep/__init__.py
libpep/libpep.cpython-38-x86_64-linux-gnu.so
libpep_py-0.11.0.dist-info/METADATA
libpep_py-0.11.0.dist-info/WHEEL
libpep_py-0.11.0.dist-info/licenses/LICENSE
libpep_py-0.11.0.dist-info/RECORD
