Metadata-Version: 2.4
Name: libpep-py
Version: 0.11.0
Classifier: Development Status :: 4 - Beta
Classifier: Intended Audience :: Developers
Classifier: License :: OSI Approved :: Apache Software License
Classifier: Programming Language :: Python :: 3
Classifier: Programming Language :: Python :: 3.8
Classifier: Programming Language :: Python :: 3.9
Classifier: Programming Language :: Python :: 3.10
Classifier: Programming Language :: Python :: 3.11
Classifier: Programming Language :: Python :: 3.12
Classifier: Programming Language :: Python :: 3.13
Classifier: Programming Language :: Rust
Classifier: Topic :: Security :: Cryptography
Requires-Dist: maturin>=1.0 ; extra == 'dev'
Requires-Dist: pytest>=7.0 ; extra == 'dev'
Provides-Extra: dev
License-File: LICENSE
Summary: Python bindings for libpep - implementation of PEP primitives, offering pseudonymization and encryption interfaces
Keywords: crypto,pep,pseudonymization
Home-Page: https://github.com/NOLAI/libpep
Author-email: Bernard van Gastel <bvgastel@bitpowder.com>, Job Doesburg <job@jobdoesburg.nl>
License: Apache-2.0
Requires-Python: >=3.8
Project-URL: Documentation, https://docs.rs/libpep
Project-URL: Homepage, https://github.com/NOLAI/libpep
Project-URL: Repository, https://github.com/NOLAI/libpep
